README.rst
setup.cfg
setup.py
thriftdomain/__init__.py
thriftdomain/multisource.py
thriftdomain.egg-info/PKG-INFO
thriftdomain.egg-info/SOURCES.txt
thriftdomain.egg-info/dependency_links.txt
thriftdomain.egg-info/not-zip-safe
thriftdomain.egg-info/requires.txt
thriftdomain.egg-info/top_level.txt