Metadata-Version: 1.1
Name: thriftdomain
Version: 1.2.0
Summary: Sphinx domain for Thrift
Home-page: http://bitbucket.org/bio-plus/sphinx-thriftdomain
Author: Tom Davis
Author-email: tom@neumitra.com
License: Apache
Platform: any
Classifier: Development Status :: 4 - Beta
Classifier: Environment :: Console
Classifier: Environment :: Web Environment
Classifier: Intended Audience :: Developers
Classifier: License :: OSI Approved :: Apache Software License
Classifier: Operating System :: OS Independent
Classifier: Programming Language :: Python
Classifier: Topic :: Documentation
Classifier: Topic :: Utilities
